[
    {
        "week_number": 1,
        "title": "HTML5, CSS3, & Responsive Web Design",
        "description": "<div class='space-y-6 text-sm text-gray-700 dark:text-gray-300'>\n    <div>\n        <h4 class='font-bold text-base text-emerald-600 dark:text-emerald-400 border-b pb-1 mb-2'>Objective</h4>\n        <p>Master modern semantic HTML5 structures, advanced CSS layout techniques (Flexbox and Grid), and responsive design principles for multi-device compatibility.</p>\n    </div>\n\n    <div>\n        <h4 class='font-bold text-base text-blue-600 dark:text-blue-400 border-b pb-1 mb-2'>Learning Phase</h4>\n        <div class='grid grid-cols-1 md:grid-cols-2 gap-4'>\n            <div>\n                <span class='font-semibold text-gray-900 dark:text-white'>1. Main Topics</span>\n                <ul class='list-disc pl-5 space-y-1 mt-1'>\n                    <li>Semantic HTML5 & Accessibility (a11y)</li>\n                    <li>Advanced CSS Flexbox & Grid Layouts</li>\n                </ul>\n            </div>\n            <div>\n                <span class='font-semibold text-gray-900 dark:text-white'>2. Detailed Concepts</span>\n                <ul class='list-disc pl-5 space-y-1 mt-1'>\n                    <li>Media queries and mobile-first workflow</li>\n                    <li>CSS custom properties (variables) and pseudo-classes</li>\n                </ul>\n            </div>\n        </div>\n        <div class='mt-4'>\n            <span class='font-semibold text-gray-900 dark:text-white'>Learning Resources:</span>\n            <ul class='list-disc pl-5 space-y-1 mt-1'>\n                <li>MDN Web Docs - CSS – <a href='https://developer.mozilla.org/en-US/docs/Web/CSS' target='_blank' class='text-indigo-600 hover:underline'>https://developer.mozilla.org/en-US/docs/Web/CSS</a></li>\n            </ul>\n        </div>\n    </div>\n\n    <div>\n        <h4 class='font-bold text-base text-purple-600 dark:text-purple-400 border-b pb-1 mb-2'>Practical Implementation</h4>\n        <div class='bg-gray-50 dark:bg-gray-900/50 p-4 rounded-xl space-y-3'>\n            <p class='font-semibold text-indigo-600 dark:text-indigo-400'>Project Task: Responsive Landing Page</p>\n            <p class='text-sm text-gray-700 dark:text-gray-300'>Build a pixel-perfect, fully responsive landing page using semantic HTML5 and modern CSS Grid/Flexbox with mobile-first styling.</p>\n        </div>\n    </div>\n\n    <div>\n        <h4 class='font-bold text-base text-amber-600 dark:text-amber-400 border-b pb-1 mb-2'>Deliverables</h4>\n        <ul class='list-decimal pl-5 space-y-1'>\n            <li><strong style='color: #e11d48;'>Live Demo URL (Vercel / Netlify) & Public GitHub Repository URL (MANDATORY / MUST)</strong></li>\n            <li>Source code directory containing well-organized HTML and CSS files.</li>\n            <li>Detailed README explaining setup commands.</li>\n        </ul>\n    </div>\n\n    <div>\n        <h4 class='font-bold text-base text-rose-600 dark:text-rose-400 border-b pb-1 mb-2'>Learning Outcomes</h4>\n        <p>Gain hands-on proficiency in structuring clean web layouts that adapt seamlessly across mobile, tablet, and desktop viewports.</p>\n    </div>\n</div>"
    },
    {
        "week_number": 2,
        "title": "Modern JavaScript (ES6+) & DOM Manipulation",
        "description": "<div class='space-y-6 text-sm text-gray-700 dark:text-gray-300'>\n    <div>\n        <h4 class='font-bold text-base text-emerald-600 dark:text-emerald-400 border-b pb-1 mb-2'>Objective</h4>\n        <p>Understand asynchronous JavaScript, ES6+ features, and interactive DOM manipulation to build dynamic client-side web behavior.</p>\n    </div>\n\n    <div>\n        <h4 class='font-bold text-base text-blue-600 dark:text-blue-400 border-b pb-1 mb-2'>Learning Phase</h4>\n        <div class='grid grid-cols-1 md:grid-cols-2 gap-4'>\n            <div>\n                <span class='font-semibold text-gray-900 dark:text-white'>1. Main Topics</span>\n                <ul class='list-disc pl-5 space-y-1 mt-1'>\n                    <li>ES6+ Features (Arrow Functions, Destructuring, Spread/Rest)</li>\n                    <li>DOM Manipulation & Event Handling</li>\n                </ul>\n            </div>\n            <div>\n                <span class='font-semibold text-gray-900 dark:text-white'>2. Detailed Concepts</span>\n                <ul class='list-disc pl-5 space-y-1 mt-1'>\n                    <li>Asynchronous JavaScript (Promises, async/await, Fetch API)</li>\n                    <li>Event bubbling, delegation, and local storage management</li>\n                </ul>\n            </div>\n        </div>\n        <div class='mt-4'>\n            <span class='font-semibold text-gray-900 dark:text-white'>Learning Resources:</span>\n            <ul class='list-disc pl-5 space-y-1 mt-1'>\n                <li>JavaScript.info – <a href='https://javascript.info/' target='_blank' class='text-indigo-600 hover:underline'>https://javascript.info/</a></li>\n            </ul>\n        </div>\n    </div>\n\n    <div>\n        <h4 class='font-bold text-base text-purple-600 dark:text-purple-400 border-b pb-1 mb-2'>Practical Implementation</h4>\n        <div class='bg-gray-50 dark:bg-gray-900/50 p-4 rounded-xl space-y-3'>\n            <p class='font-semibold text-indigo-600 dark:text-indigo-400'>Project Task: Interactive Web Application (e.g., Weather or Task Tracker)</p>\n            <p class='text-sm text-gray-700 dark:text-gray-300'>Build an interactive application that fetches live data from an external public REST API and updates the DOM dynamically based on user input.</p>\n        </div>\n    </div>\n\n    <div>\n        <h4 class='font-bold text-base text-amber-600 dark:text-amber-400 border-b pb-1 mb-2'>Deliverables</h4>\n        <ul class='list-decimal pl-5 space-y-1'>\n            <li><strong style='color: #e11d48;'>Live Demo URL (Vercel / Netlify) & Public GitHub Repository URL (MANDATORY / MUST)</strong></li>\n            <li>JavaScript modules implementation handling API requests and DOM elements.</li>\n            <li>Detailed README explaining setup commands.</li>\n        </ul>\n    </div>\n\n    <div>\n        <h4 class='font-bold text-base text-rose-600 dark:text-rose-400 border-b pb-1 mb-2'>Learning Outcomes</h4>\n        <p>Master modern scripting practices and asynchronous data handling required for interactive frontend architectures.</p>\n    </div>\n</div>"
    },
    {
        "week_number": 3,
        "title": "Advanced JavaScript & Working with APIs",
        "description": "<div class='space-y-6 text-sm text-gray-700 dark:text-gray-300'>\n    <div>\n        <h4 class='font-bold text-base text-emerald-600 dark:text-emerald-400 border-b pb-1 mb-2'>Objective</h4>\n        <p>Deepen advanced JavaScript patterns, closures, prototypes, error handling, and robust RESTful API integration workflows.</p>\n    </div>\n\n    <div>\n        <h4 class='font-bold text-base text-blue-600 dark:text-blue-400 border-b pb-1 mb-2'>Learning Phase</h4>\n        <div class='grid grid-cols-1 md:grid-cols-2 gap-4'>\n            <div>\n                <span class='font-semibold text-gray-900 dark:text-white'>1. Main Topics</span>\n                <ul class='list-disc pl-5 space-y-1 mt-1'>\n                    <li>Advanced JS Patterns (Closures, Scope, Prototypes)</li>\n                    <li>RESTful API Consumption & Error Handling</li>\n                </ul>\n            </div>\n            <div>\n                <span class='font-semibold text-gray-900 dark:text-white'>2. Detailed Concepts</span>\n                <ul class='list-disc pl-5 space-y-1 mt-1'>\n                    <li>JSON parsing, HTTP status codes, and try/catch blocks</li>\n                    <li>Debouncing, throttling, and performance optimization</li>\n                </ul>\n            </div>\n        </div>\n        <div class='mt-4'>\n            <span class='font-semibold text-gray-900 dark:text-white'>Learning Resources:</span>\n            <ul class='list-disc pl-5 space-y-1 mt-1'>\n                <li>MDN JavaScript Guide – <a href='https://developer.mozilla.org/en-US/docs/Web/JavaScript/Guide' target='_blank' class='text-indigo-600 hover:underline'>https://developer.mozilla.org/en-US/docs/Web/JavaScript/Guide</a></li>\n            </ul>\n        </div>\n    </div>\n\n    <div>\n        <h4 class='font-bold text-base text-purple-600 dark:text-purple-400 border-b pb-1 mb-2'>Practical Implementation</h4>\n        <div class='bg-gray-50 dark:bg-gray-900/50 p-4 rounded-xl space-y-3'>\n            <p class='font-semibold text-indigo-600 dark:text-indigo-400'>Project Task: Dynamic API Explorer App</p>\n            <p class='text-sm text-gray-700 dark:text-gray-300'>Create an app that queries data from public APIs, featuring search filters, pagination logic, and error boundaries.</p>\n        </div>\n    </div>\n\n    <div>\n        <h4 class='font-bold text-base text-amber-600 dark:text-amber-400 border-b pb-1 mb-2'>Deliverables</h4>\n        <ul class='list-decimal pl-5 space-y-1'>\n            <li><strong style='color: #e11d48;'>Live Demo URL (Vercel / Netlify) & Public GitHub Repository URL (MANDATORY / MUST)</strong></li>\n            <li>Source code with structured API utility services and error handling scripts.</li>\n            <li>Detailed README explaining setup commands.</li>\n        </ul>\n    </div>\n\n    <div>\n        <h4 class='font-bold text-base text-rose-600 dark:text-rose-400 border-b pb-1 mb-2'>Learning Outcomes</h4>\n        <p>Acquire advanced scripting logic and resilient error management skills when connecting client apps with remote backends.</p>\n    </div>\n</div>"
    },
    {
        "week_number": 4,
        "title": "React.js Fundamentals & Component Architecture",
        "description": "<div class='space-y-6 text-sm text-gray-700 dark:text-gray-300'>\n    <div>\n        <h4 class='font-bold text-base text-emerald-600 dark:text-emerald-400 border-b pb-1 mb-2'>Objective</h4>\n        <p>Learn React fundamentals, component-driven development, state management hooks, and props flow to build reusable user interfaces.</p>\n    </div>\n\n    <div>\n        <h4 class='font-bold text-base text-blue-600 dark:text-blue-400 border-b pb-1 mb-2'>Learning Phase</h4>\n        <div class='grid grid-cols-1 md:grid-cols-2 gap-4'>\n            <div>\n                <span class='font-semibold text-gray-900 dark:text-white'>1. Main Topics</span>\n                <ul class='list-disc pl-5 space-y-1 mt-1'>\n                    <li>JSX, Components, and Props</li>\n                    <li>React Hooks (useState, useEffect)</li>\n                </ul>\n            </div>\n            <div>\n                <span class='font-semibold text-gray-900 dark:text-white'>2. Detailed Concepts</span>\n                <ul class='list-disc pl-5 space-y-1 mt-1'>\n                    <li>Component lifecycle and side-effect management</li>\n                    <li>Lifting state up and handling user form inputs</li>\n                </ul>\n            </div>\n        </div>\n        <div class='mt-4'>\n            <span class='font-semibold text-gray-900 dark:text-white'>Learning Resources:</span>\n            <ul class='list-disc pl-5 space-y-1 mt-1'>\n                <li>React Official Documentation – <a href='https://react.dev/' target='_blank' class='text-indigo-600 hover:underline'>https://react.dev/</a></li>\n            </ul>\n        </div>\n    </div>\n\n    <div>\n        <h4 class='font-bold text-base text-purple-600 dark:text-purple-400 border-b pb-1 mb-2'>Practical Implementation</h4>\n        <div class='bg-gray-50 dark:bg-gray-900/50 p-4 rounded-xl space-y-3'>\n            <p class='font-semibold text-indigo-600 dark:text-indigo-400'>Project Task: React Dashboard or E-Commerce Catalog</p>\n            <p class='text-sm text-gray-700 dark:text-gray-300'>Create a modular React application featuring multiple components, dynamic lists, search filters, and reactive state tracking.</p>\n        </div>\n    </div>\n\n    <div>\n        <h4 class='font-bold text-base text-amber-600 dark:text-amber-400 border-b pb-1 mb-2'>Deliverables</h4>\n        <ul class='list-decimal pl-5 space-y-1'>\n            <li><strong style='color: #e11d48;'>Live Demo URL (Vercel / Netlify) & Public GitHub Repository URL (MANDATORY / MUST)</strong></li>\n            <li>Modular React application build folder structure.</li>\n            <li>Detailed README explaining setup commands.</li>\n        </ul>\n    </div>\n\n    <div>\n        <h4 class='font-bold text-base text-rose-600 dark:text-rose-400 border-b pb-1 mb-2'>Learning Outcomes</h4>\n        <p>Gain professional expertise in building scalable component hierarchies and managing application state efficiently using React.</p>\n    </div>\n</div>"
    },
    {
        "week_number": 5,
        "title": "Routing & Advanced State Management (Context API)",
        "description": "<div class='space-y-6 text-sm text-gray-700 dark:text-gray-300'>\n    <div>\n        <h4 class='font-bold text-base text-emerald-600 dark:text-emerald-400 border-b pb-1 mb-2'>Objective</h4>\n        <p>Implement single-page navigation with React Router and handle complex global states cleanly using React Context API.</p>\n    </div>\n\n    <div>\n        <h4 class='font-bold text-base text-blue-600 dark:text-blue-400 border-b pb-1 mb-2'>Learning Phase</h4>\n        <div class='grid grid-cols-1 md:grid-cols-2 gap-4'>\n            <div>\n                <span class='font-semibold text-gray-900 dark:text-white'>1. Main Topics</span>\n                <ul class='list-disc pl-5 space-y-1 mt-1'>\n                    <li>React Router (Nested Routes, Params)</li>\n                    <li>Global State Management via Context API</li>\n                </ul>\n            </div>\n            <div>\n                <span class='font-semibold text-gray-900 dark:text-white'>2. Detailed Concepts</span>\n                <ul class='list-disc pl-5 space-y-1 mt-1'>\n                    <li>Avoiding prop drilling with custom hooks and context providers</li>\n                    <li>Protected routes and layout wrappers</li>\n                </ul>\n            </div>\n        </div>\n        <div class='mt-4'>\n            <span class='font-semibold text-gray-900 dark:text-white'>Learning Resources:</span>\n            <ul class='list-disc pl-5 space-y-1 mt-1'>\n                <li>React Router Documentation – <a href='https://reactrouter.com/' target='_blank' class='text-indigo-600 hover:underline'>https://reactrouter.com/</a></li>\n            </ul>\n        </div>\n    </div>\n\n    <div>\n        <h4 class='font-bold text-base text-purple-600 dark:text-purple-400 border-b pb-1 mb-2'>Practical Implementation</h4>\n        <div class='bg-gray-50 dark:bg-gray-900/50 p-4 rounded-xl space-y-3'>\n            <p class='font-semibold text-indigo-600 dark:text-indigo-400'>Project Task: Multi-Page App with Authentication Flow</p>\n            <p class='text-sm text-gray-700 dark:text-gray-300'>Build a multi-page app with React Router, utilizing Context API for user authentication and global theme states.</p>\n        </div>\n    </div>\n\n    <div>\n        <h4 class='font-bold text-base text-amber-600 dark:text-amber-400 border-b pb-1 mb-2'>Deliverables</h4>\n        <ul class='list-decimal pl-5 space-y-1'>\n            <li><strong style='color: #e11d48;'>Live Demo URL (Vercel / Netlify) & Public GitHub Repository URL (MANDATORY / MUST)</strong></li>\n            <li>React source files implementing routing configuration and context providers.</li>\n            <li>Detailed README explaining setup commands.</li>\n        </ul>\n    </div>\n\n    <div>\n        <h4 class='font-bold text-base text-rose-600 dark:text-rose-400 border-b pb-1 mb-2'>Learning Outcomes</h4>\n        <p>Master multi-view application architecture and state sharing patterns without prop drilling overhead.</p>\n    </div>\n</div>"
    },
    {
        "week_number": 6,
        "title": "Tailwind CSS & Modern UI/UX Design Systems",
        "description": "<div class='space-y-6 text-sm text-gray-700 dark:text-gray-300'>\n    <div>\n        <h4 class='font-bold text-base text-emerald-600 dark:text-emerald-400 border-b pb-1 mb-2'>Objective</h4>\n        <p>Style modern React applications efficiently using Tailwind CSS utility classes and design accessible user interfaces.</p>\n    </div>\n\n    <div>\n        <h4 class='font-bold text-base text-blue-600 dark:text-blue-400 border-b pb-1 mb-2'>Learning Phase</h4>\n        <div class='grid grid-cols-1 md:grid-cols-2 gap-4'>\n            <div>\n                <span class='font-semibold text-gray-900 dark:text-white'>1. Main Topics</span>\n                <ul class='list-disc pl-5 space-y-1 mt-1'>\n                    <li>Tailwind CSS Utility-First Framework</li>\n                    <li>Responsive Design & Dark Mode Implementation</li>\n                </ul>\n            </div>\n            <div>\n                <span class='font-semibold text-gray-900 dark:text-white'>2. Detailed Concepts</span>\n                <ul class='list-disc pl-5 space-y-1 mt-1'>\n                    <li>Custom configuration, flex/grid utilities, and component styling</li>\n                    <li>Building accessible modals, dropdowns, and navigation bars</li>\n                </ul>\n            </div>\n        </div>\n        <div class='mt-4'>\n            <span class='font-semibold text-gray-900 dark:text-white'>Learning Resources:</span>\n            <ul class='list-disc pl-5 space-y-1 mt-1'>\n                <li>Tailwind CSS Documentation – <a href='https://tailwindcss.com/docs' target='_blank' class='text-indigo-600 hover:underline'>https://tailwindcss.com/docs</a></li>\n            </ul>\n        </div>\n    </div>\n\n    <div>\n        <h4 class='font-bold text-base text-purple-600 dark:text-purple-400 border-b pb-1 mb-2'>Practical Implementation</h4>\n        <div class='bg-gray-50 dark:bg-gray-900/50 p-4 rounded-xl space-y-3'>\n            <p class='font-semibold text-indigo-600 dark:text-indigo-400'>Project Task: Tailwind UI Dashboard Redesign</p>\n            <p class='text-sm text-gray-700 dark:text-gray-300'>Refactor a React application using Tailwind CSS to include responsive grids, card components, and an interactive dark mode toggle.</p>\n        </div>\n    </div>\n\n    <div>\n        <h4 class='font-bold text-base text-amber-600 dark:text-amber-400 border-b pb-1 mb-2'>Deliverables</h4>\n        <ul class='list-decimal pl-5 space-y-1'>\n            <li><strong style='color: #e11d48;'>Live Demo URL (Vercel / Netlify) & Public GitHub Repository URL (MANDATORY / MUST)</strong></li>\n            <li>Tailwind configured React app codebase with responsive layouts.</li>\n            <li>Detailed README explaining setup commands.</li>\n        </ul>\n    </div>\n\n    <div>\n        <h4 class='font-bold text-base text-rose-600 dark:text-rose-400 border-b pb-1 mb-2'>Learning Outcomes</h4>\n        <p>Gain proficiency in rapid styling workflows and modern UI design systems using Tailwind utility frameworks.</p>\n    </div>\n</div>"
    },
    {
        "week_number": 7,
        "title": "Performance Optimization, Forms & API Integration",
        "description": "<div class='space-y-6 text-sm text-gray-700 dark:text-gray-300'>\n    <div>\n        <h4 class='font-bold text-base text-emerald-600 dark:text-emerald-400 border-b pb-1 mb-2'>Objective</h4>\n        <p>Handle complex form validation, manage API requests efficiently, and optimize frontend rendering performance.</p>\n    </div>\n\n    <div>\n        <h4 class='font-bold text-base text-blue-600 dark:text-blue-400 border-b pb-1 mb-2'>Learning Phase</h4>\n        <div class='grid grid-cols-1 md:grid-cols-2 gap-4'>\n            <div>\n                <span class='font-semibold text-gray-900 dark:text-white'>1. Main Topics</span>\n                <ul class='list-disc pl-5 space-y-1 mt-1'>\n                    <li>Advanced Form Validation & Custom Hooks</li>\n                    <li>Performance Optimization (Memoization, Lazy Loading)</li>\n                </ul>\n            </div>\n            <div>\n                <span class='font-semibold text-gray-900 dark:text-white'>2. Detailed Concepts</span>\n                <ul class='list-disc pl-5 space-y-1 mt-1'>\n                    <li>React.memo, useMemo, useCallback optimization patterns</li>\n                    <li>Form state management and validation libraries</li>\n                </ul>\n            </div>\n        </div>\n        <div class='mt-4'>\n            <span class='font-semibold text-gray-900 dark:text-white'>Learning Resources:</span>\n            <ul class='list-disc pl-5 space-y-1 mt-1'>\n                <li>React Performance Optimization Guide – <a href='https://react.dev/learn/render-and-commit' target='_blank' class='text-indigo-600 hover:underline'>https://react.dev/learn/render-and-commit</a></li>\n            </ul>\n        </div>\n    </div>\n\n    <div>\n        <h4 class='font-bold text-base text-purple-600 dark:text-purple-400 border-b pb-1 mb-2'>Practical Implementation</h4>\n        <div class='bg-gray-50 dark:bg-gray-900/50 p-4 rounded-xl space-y-3'>\n            <p class='font-semibold text-indigo-600 dark:text-indigo-400'>Project Task: Optimized Data-Intensive Application</p>\n            <p class='text-sm text-gray-700 dark:text-gray-300'>Build a data-heavy search dashboard incorporating memoization hooks to prevent unnecessary re-renders and smooth out form validation loops.</p>\n        </div>\n    </div>\n\n    <div>\n        <h4 class='font-bold text-base text-amber-600 dark:text-amber-400 border-b pb-1 mb-2'>Deliverables</h4>\n        <ul class='list-decimal pl-5 space-y-1'>\n            <li><strong style='color: #e11d48;'>Live Demo URL (Vercel / Netlify) & Public GitHub Repository URL (MANDATORY / MUST)</strong></li>\n            <li>Source code optimized with memoization and validation logic.</li>\n            <li>Detailed README explaining setup commands.</li>\n        </ul>\n    </div>\n\n    <div>\n        <h4 class='font-bold text-base text-rose-600 dark:text-rose-400 border-b pb-1 mb-2'>Learning Outcomes</h4>\n        <p>Understand how to build production-grade forms and troubleshoot rendering performance bottlenecks in React apps.</p>\n    </div>\n</div>"
    },
    {
        "week_number": 8,
        "title": "Capstone Project & Cloud Deployment",
        "description": "<div class='space-y-6 text-sm text-gray-700 dark:text-gray-300'>\n    <div>\n        <h4 class='font-bold text-base text-emerald-600 dark:text-emerald-400 border-b pb-1 mb-2'>Objective</h4>\n        <p>Integrate all learned frontend concepts into a complete, portfolio-ready capstone application deployed live on Vercel or Netlify.</p>\n    </div>\n\n    <div>\n        <h4 class='font-bold text-base text-blue-600 dark:text-blue-400 border-b pb-1 mb-2'>Learning Phase</h4>\n        <div class='grid grid-cols-1 md:grid-cols-2 gap-4'>\n            <div>\n                <span class='font-semibold text-gray-900 dark:text-white'>1. Main Topics</span>\n                <ul class='list-disc pl-5 space-y-1 mt-1'>\n                    <li>End-to-End Frontend Integration</li>\n                    <li>Production Build Testing & Cloud Deployment</li>\n                </ul>\n            </div>\n            <div>\n                <span class='font-semibold text-gray-900 dark:text-white'>2. Detailed Concepts</span>\n                <ul class='list-disc pl-5 space-y-1 mt-1'>\n                    <li>Environment variables configuration and build artifact optimization</li>\n                    <li>Continuous deployment workflows via GitHub with Vercel or Netlify</li>\n                </ul>\n            </div>\n        </div>\n        <div class='mt-4'>\n            <span class='font-semibold text-gray-900 dark:text-white'>Learning Resources:</span>\n            <ul class='list-disc pl-5 space-y-1 mt-1'>\n                <li>Vercel Deployment Documentation – <a href='https://vercel.com/docs' target='_blank' class='text-indigo-600 hover:underline'>https://vercel.com/docs</a></li>\n            </ul>\n        </div>\n    </div>\n\n    <div>\n        <h4 class='font-bold text-base text-purple-600 dark:text-purple-400 border-b pb-1 mb-2'>Practical Implementation</h4>\n        <div class='bg-gray-50 dark:bg-gray-900/50 p-4 rounded-xl space-y-3'>\n            <p class='font-semibold text-indigo-600 dark:text-indigo-400'>Project Task: Capstone React Web Application</p>\n            <p class='text-sm text-gray-700 dark:text-gray-300'>Develop a fully functional, multi-feature React app with custom styling, API integrations, and publish the live production link.</p>\n        </div>\n    </div>\n\n    <div>\n        <h4 class='font-bold text-base text-amber-600 dark:text-amber-400 border-b pb-1 mb-2'>Deliverables</h4>\n        <ul class='list-decimal pl-5 space-y-1'>\n            <li><strong style='color: #e11d48;'>Live Demo URL (Vercel / Netlify) & Public GitHub Repository URL (MANDATORY / MUST)</strong></li>\n            <li>Fully functional and deployed web application link.</li>\n            <li>Detailed README explaining setup commands.</li>\n        </ul>\n    </div>\n\n    <div>\n        <h4 class='font-bold text-base text-rose-600 dark:text-rose-400 border-b pb-1 mb-2'>Learning Outcomes</h4>\n        <p>Successfully demonstrate professional competency in modern frontend engineering by launching a production-grade web project.</p>\n    </div>\n</div>"
    }
]